{
  "_totalAll": 8,
  "_totalChanged": 8,
  "_totalNew": 0,
  "_totalRemoved": 0,
  "all": {
    "alterguardian_phase1_lunar.zip": "Changed",
    "databundles/anim_dynamic.zip/anim/dynamic/berrybush_cawnival.zip": "Changed",
    "databundles/anim_dynamic.zip/anim/dynamic/wathgrithr_western.zip": "Changed",
    "ds_spider2_caves.zip": "Changed",
    "dynamic/berrybush_cawnival.dyn": "Changed",
    "dynamic/wathgrithr_western.dyn": "Changed",
    "wagboss_lunar.zip": "Changed",
    "wagboss_robot.zip": "Changed"
  },
  "changed": [
    "alterguardian_phase1_lunar.zip",
    "databundles/anim_dynamic.zip/anim/dynamic/berrybush_cawnival.zip",
    "databundles/anim_dynamic.zip/anim/dynamic/wathgrithr_western.zip",
    "ds_spider2_caves.zip",
    "dynamic/berrybush_cawnival.dyn",
    "dynamic/wathgrithr_western.dyn",
    "wagboss_lunar.zip",
    "wagboss_robot.zip"
  ],
  "new": [],
  "removed": []
}